[{"__symbolic":"module","version":3,"metadata":{"EncounterViewerModule":{"__symbolic":"class","decorators":[{"__symbolic":"call","expression":{"__symbolic":"reference","module":"@angular/core","name":"NgModule"},"arguments":[{"declarations":[{"__symbolic":"reference","module":"./encounter-view/encounter-viewer.component","name":"EncounterViewerComponent"},{"__symbolic":"reference","module":"./encounter-details-view/encounter-details.component","name":"EncounterDetailsComponent"},{"__symbolic":"reference","module":"./encounter-container/encounter-container.component","name":"EncounterContainerComponent"}],"imports":[{"__symbolic":"reference","module":"@angular/common","name":"CommonModule"}],"providers":[{"__symbolic":"reference","module":"./encounter-viewer.service","name":"EncounterViewerService"}],"exports":[{"__symbolic":"reference","module":"./encounter-container/encounter-container.component","name":"EncounterContainerComponent"}]}]}]}}},{"__symbolic":"module","version":1,"metadata":{"EncounterViewerModule":{"__symbolic":"class","decorators":[{"__symbolic":"call","expression":{"__symbolic":"reference","module":"@angular/core","name":"NgModule"},"arguments":[{"declarations":[{"__symbolic":"reference","module":"./encounter-view/encounter-viewer.component","name":"EncounterViewerComponent"},{"__symbolic":"reference","module":"./encounter-details-view/encounter-details.component","name":"EncounterDetailsComponent"},{"__symbolic":"reference","module":"./encounter-container/encounter-container.component","name":"EncounterContainerComponent"}],"imports":[{"__symbolic":"reference","module":"@angular/common","name":"CommonModule"}],"providers":[{"__symbolic":"reference","module":"./encounter-viewer.service","name":"EncounterViewerService"}],"exports":[{"__symbolic":"reference","module":"./encounter-container/encounter-container.component","name":"EncounterContainerComponent"}]}]}]}}}]