[{"__symbolic":"module","version":3,"metadata":{"FilePreviewComponent":{"__symbolic":"class","decorators":[{"__symbolic":"call","expression":{"__symbolic":"reference","module":"@angular/core","name":"Component"},"arguments":[{"selector":"file-preview","styles":[""],"template":"<div *ngIf=\"innerValue\">\n              <img class=\"img-responsive\"\n                [src]=\"innerValue | secure:this._dataSource.fetchFile\" alt=\"image\" />\n                </div>","providers":[{"provide":{"__symbolic":"reference","module":"@angular/forms","name":"NG_VALUE_ACCESSOR"},"useExisting":{"__symbolic":"reference","name":"FilePreviewComponent"},"multi":true}]}]}],"members":{"source":[{"__symbolic":"property","decorators":[{"__symbolic":"call","expression":{"__symbolic":"reference","module":"@angular/core","name":"Input"}}]}],"dataSource":[{"__symbolic":"property","decorators":[{"__symbolic":"call","expression":{"__symbolic":"reference","module":"@angular/core","name":"Input"}}]}],"__ctor__":[{"__symbolic":"constructor","parameters":[{"__symbolic":"reference","module":"../encounter-viewer.service","name":"EncounterViewerService"}]}],"writeValue":[{"__symbolic":"method"}],"registerOnChange":[{"__symbolic":"method"}],"registerOnTouched":[{"__symbolic":"method"}],"onBlur":[{"__symbolic":"method"}],"onChange":[{"__symbolic":"method"}]}}}},{"__symbolic":"module","version":1,"metadata":{"FilePreviewComponent":{"__symbolic":"class","decorators":[{"__symbolic":"call","expression":{"__symbolic":"reference","module":"@angular/core","name":"Component"},"arguments":[{"selector":"file-preview","styles":[""],"template":"<div *ngIf=\"innerValue\">\n              <img class=\"img-responsive\"\n                [src]=\"innerValue | secure:this._dataSource.fetchFile\" alt=\"image\" />\n                </div>","providers":[{"provide":{"__symbolic":"reference","module":"@angular/forms","name":"NG_VALUE_ACCESSOR"},"useExisting":{"__symbolic":"reference","name":"FilePreviewComponent"},"multi":true}]}]}],"members":{"source":[{"__symbolic":"property","decorators":[{"__symbolic":"call","expression":{"__symbolic":"reference","module":"@angular/core","name":"Input"}}]}],"dataSource":[{"__symbolic":"property","decorators":[{"__symbolic":"call","expression":{"__symbolic":"reference","module":"@angular/core","name":"Input"}}]}],"__ctor__":[{"__symbolic":"constructor","parameters":[{"__symbolic":"reference","module":"../encounter-viewer.service","name":"EncounterViewerService"}]}],"writeValue":[{"__symbolic":"method"}],"registerOnChange":[{"__symbolic":"method"}],"registerOnTouched":[{"__symbolic":"method"}],"onBlur":[{"__symbolic":"method"}],"onChange":[{"__symbolic":"method"}]}}}}]